ontos/__init__.py
ontos/__main__.py
ontos/cli.py
ontos/_hooks/__init__.py
ontos/_hooks/pre-commit
ontos/_hooks/pre-push
ontos/_scripts/__init__.py
ontos/_scripts/ontos_config.py
ontos/_scripts/ontos_config_defaults.py
ontos/_scripts/ontos_consolidate.py
ontos/_scripts/ontos_end_session.py
ontos/_scripts/ontos_generate_context_map.py
ontos/_scripts/ontos_legacy_cli.py
ontos/_scripts/ontos_maintain.py
ontos/_scripts/ontos_migrate_schema.py
ontos/_scripts/ontos_pre_commit_check.py
ontos/_scripts/ontos_pre_push_check.py
ontos/_scripts/ontos_promote.py
ontos/_scripts/ontos_query.py
ontos/_scripts/ontos_scaffold.py
ontos/_scripts/ontos_stub.py
ontos/_scripts/ontos_update.py
ontos/_scripts/ontos_verify.py
ontos/_templates/__init__.py
ontos/_templates/common_concepts_template.md
ontos/_templates/decision_history_template.md
ontos/_templates/ontos_config.py.template
ontos/_templates/templates.py
ontos/commands/__init__.py
ontos/commands/agents.py
ontos/commands/consolidate.py
ontos/commands/doctor.py
ontos/commands/env.py
ontos/commands/export.py
ontos/commands/export_claude.py
ontos/commands/export_data.py
ontos/commands/hook.py
ontos/commands/init.py
ontos/commands/log.py
ontos/commands/map.py
ontos/commands/migrate.py
ontos/commands/migrate_cmd.py
ontos/commands/migration_report.py
ontos/commands/promote.py
ontos/commands/query.py
ontos/commands/scaffold.py
ontos/commands/stub.py
ontos/commands/verify.py
ontos/core/__init__.py
ontos/core/cache.py
ontos/core/config.py
ontos/core/context.py
ontos/core/curation.py
ontos/core/frontmatter.py
ontos/core/graph.py
ontos/core/history.py
ontos/core/migration.py
ontos/core/ontology.py
ontos/core/paths.py
ontos/core/proposals.py
ontos/core/schema.py
ontos/core/snapshot.py
ontos/core/staleness.py
ontos/core/suggestions.py
ontos/core/tokens.py
ontos/core/types.py
ontos/core/validation.py
ontos/io/__init__.py
ontos/io/config.py
ontos/io/files.py
ontos/io/git.py
ontos/io/obsidian.py
ontos/io/toml.py
ontos/io/yaml.py
ontos-3.2.0.dist-info/licenses/LICENSE
ontos-3.2.0.dist-info/METADATA
ontos-3.2.0.dist-info/WHEEL
ontos-3.2.0.dist-info/entry_points.txt
ontos-3.2.0.dist-info/top_level.txt
ontos-3.2.0.dist-info/RECORD
