Metadata-Version: 2.4
Name: ontos
Version: 3.2.0
Summary: Local-first documentation management for AI-assisted development
Author-email: Ontos Project <ohjona@users.noreply.github.com>
License-Expression: Apache-2.0
Project-URL: Homepage, https://github.com/ohjona/Project-Ontos
Project-URL: Documentation, https://github.com/ohjona/Project-Ontos/tree/main/docs
Project-URL: Repository, https://github.com/ohjona/Project-Ontos
Project-URL: Issues, https://github.com/ohjona/Project-Ontos/issues
Keywords: documentation,ai,context,llm,developer-tools
Classifier: Development Status :: 3 - Alpha
Classifier: Environment :: Console
Classifier: Intended Audience :: Developers
Classifier: Operating System :: OS Independent
Classifier: Programming Language :: Python :: 3
Classifier: Programming Language :: Python :: 3.9
Classifier: Programming Language :: Python :: 3.10
Classifier: Programming Language :: Python :: 3.11
Classifier: Programming Language :: Python :: 3.12
Classifier: Topic :: Documentation
Classifier: Topic :: Software Development :: Documentation
Requires-Python: >=3.9
License-File: LICENSE
Requires-Dist: pyyaml<7.0,>=6.0
Requires-Dist: tomli<3.0,>=2.0.1; python_version < "3.11"
Provides-Extra: dev
Requires-Dist: pytest<9.0,>=7.0; extra == "dev"
Requires-Dist: pytest-cov<6.0,>=4.0; extra == "dev"
Requires-Dist: pre-commit<5.0,>=3.0; extra == "dev"
Provides-Extra: mcp
Requires-Dist: pydantic<3.0,>=2.0; extra == "mcp"
Dynamic: license-file
